flask_jsonlocale.py
Flask_JSONLocale-1.9.dist-info/DESCRIPTION.rst
Flask_JSONLocale-1.9.dist-info/METADATA
Flask_JSONLocale-1.9.dist-info/RECORD
Flask_JSONLocale-1.9.dist-info/WHEEL
Flask_JSONLocale-1.9.dist-info/metadata.json
Flask_JSONLocale-1.9.dist-info/top_level.txt
